README.txt
setup.py
genix/__init__.py
genix/colours.py
genix/setup.py
genix/ui_main.py
genix.egg-info/PKG-INFO
genix.egg-info/SOURCES.txt
genix.egg-info/dependency_links.txt
genix.egg-info/requires.txt
genix.egg-info/top_level.txt
genix/components/ui_component.py
genix/components/ui_text.py
genix/constraints/center_x.py
genix/constraints/center_y.py
genix/constraints/centered.py
genix/constraints/constraint.py
genix/constraints/height_ratio.py
genix/constraints/horizontal.py
genix/constraints/padding.py
genix/constraints/relative_height.py
genix/constraints/relative_width.py
genix/constraints/vertical.py
genix/constraints/width_ratio.py
genix/containers/ui_container.py
genix/containers/ui_grid.py
genix/containers/ui_select_box.py
genix/containers/ui_slider.py
genix/containers/ui_window.py