Metadata-Version: 1.1
Name: genix
Version: 0.1.2
Summary: GUI library for Pygame
Home-page: https://github.com/thealec1/genix
Author: Alec Reilly
Author-email: areilly14@icloud.com
License: MIT
Keywords: pygame,interface,gui,ui
Platform: UNKNOWN
Classifier: Development Status :: 2 - Pre-Alpha
Classifier: Intended Audience :: Developers
Classifier: Topic :: Software Development :: Build Tools
Classifier: Operating System :: Microsoft :: Windows :: Windows 10
Classifier: License :: OSI Approved :: MIT License
Classifier: Programming Language :: Python :: 3
